{
  "libros": [
    {
      "name": "Binding 13",
      "price": "450.00",
      "imageUrl": "http://127.0.0.1:5500/assets/img/Libros/portada-libro1.jpg",
      "id": "1"
    },
    {
      "id": "2",
      "name": "El arte de ser nosotros",
      "price": "325.00",
      "imageUrl": "./assets/img/Libros/portada-libro2.jpg"
    },
    {
      "id": "3",
      "name": "El tiempo que tuvimos",
      "price": "260.00",
      "imageUrl": "./assets/img/Libros/portada-libro3.jpg"
    },
    {
      "id": 4,
      "name": "Orgullo y prejuicio",
      "price": "280.00",
      "imageUrl": "./assets/img/Libros/portada-libro6.jpg"
    }
  ]
}